corded/logging/__init__.py
corded_logger-1.0.0.dist-info/LICENSE
corded_logger-1.0.0.dist-info/WHEEL
corded_logger-1.0.0.dist-info/METADATA
corded_logger-1.0.0.dist-info/RECORD
