Metadata-Version: 2.1
Name: corded-logger
Version: 1.0.0
Summary: A Discord webhook logger for Corded
Author: vcokltfre
Author-email: vcokltfre@gmail.com
Requires-Python: >=3.8,<4.0
Classifier: Programming Language :: Python :: 3
Classifier: Programming Language :: Python :: 3.8
Classifier: Programming Language :: Python :: 3.9
Requires-Dist: corded (>=1.3.8,<2.0.0)
Requires-Dist: loguru (>=0.5.3,<0.6.0)
